WiFi_Access/Android.py
WiFi_Access/Error.py
WiFi_Access/Linux.py
WiFi_Access/Windows.py
WiFi_Access/__init__.py
WiFi_Access/wifi.py
WiFi_Access-1.0.0.dist-info/METADATA
WiFi_Access-1.0.0.dist-info/WHEEL
WiFi_Access-1.0.0.dist-info/top_level.txt
WiFi_Access-1.0.0.dist-info/RECORD
