Metadata-Version: 2.1
Name: WiFi-Access
Version: 1.0.0
Summary: Простой инструмент для получения списка всех имён сетей WiFi и их пароля, к которым когда-либо был подключён ПК.
Home-page: https://github.com/MY-INSIDE/WiFi_Access
Author: MY_INSIDE
Author-email: my.inside.dream@gmail.com
Classifier: Programming Language :: Python :: 3
Classifier: License :: OSI Approved :: MIT License
Classifier: Operating System :: OS Independent
Requires-Python: >=3.6
